{
  "inputUrl": "https://www.instagram.com/p/DXWwp_HkZ3T/",
  "id": "3879502120530058707",
  "type": "Video",
  "shortCode": "DXWwp_HkZ3T",
  "caption": "Not the judge hitting the Shimmy Shimmy Yay challenge too 😭💍\n\n#friscophotographer #civilwedding #photography #dallasphotography #dallasphotographer\n\nVideo: @crix_cci",
  "hashtags": [
    "friscophotographer",
    "civilwedding",
    "photography",
    "dallasphotography",
    "dallasphotographer"
  ],
  "mentions": [
    "crix_cci"
  ],
  "url": "https://www.instagram.com/p/DXWwp_HkZ3T/",
  "commentsCount": 182,
  "firstComment": "What’s this judge’s handle",
  "latestComments": [
    {
      "id": "18006360017886709",
      "text": "What’s this judge’s handle",
      "ownerUsername": "_mizdee",
      "ownerProfilePicUrl": "https://instagram.fdet3-1.fna.fbcdn.net/v/t51.2885-19/158450088_3176724755946050_991854696223857199_n.jpg?stp=dst-jpg_s150x150_tt6&efg=eyJ2ZW5jb2RlX3RhZyI6InByb2ZpbGVfcGljLmRqYW5nby4xMDgwLmMyIn0&_nc_ht=instagram.fdet3-1.fna.fbcdn.net&_nc_cat=102&_nc_oc=Q6cZ2gGcDjN5npyxElfFUSdPCD6m4Fw--OXXUQKkiHtEYawpHyrrRYgiNrWm42PMKCj_G_M&_nc_ohc=gKNRE0v6niwQ7kNvwHKaq33&_nc_gid=1kEOHd-MKI879a4-KeQ-kQ&edm=APs17CUBAAAA&ccb=7-5&oh=00_Af1eH0pntZpr-QBr5MZKq0r2PjicTeP1NDnTFSFqGKme4g&oe=69F2CCD0&_nc_sid=10d13b",
      "timestamp": "2026-04-25T12:30:55.000Z",
      "repliesCount": 0,
      "replies": [],
      "likesCount": 0,
      "owner": {
        "id": "412848725",
        "is_verified": false,
        "profile_pic_url": "https://instagram.fdet3-1.fna.fbcdn.net/v/t51.2885-19/158450088_3176724755946050_991854696223857199_n.jpg?stp=dst-jpg_s150x150_tt6&efg=eyJ2ZW5jb2RlX3RhZyI6InByb2ZpbGVfcGljLmRqYW5nby4xMDgwLmMyIn0&_nc_ht=instagram.fdet3-1.fna.fbcdn.net&_nc_cat=102&_nc_oc=Q6cZ2gGcDjN5npyxElfFUSdPCD6m4Fw--OXXUQKkiHtEYawpHyrrRYgiNrWm42PMKCj_G_M&_nc_ohc=gKNRE0v6niwQ7kNvwHKaq33&_nc_gid=1kEOHd-MKI879a4-KeQ-kQ&edm=APs17CUBAAAA&ccb=7-5&oh=00_Af1eH0pntZpr-QBr5MZKq0r2PjicTeP1NDnTFSFqGKme4g&oe=69F2CCD0&_nc_sid=10d13b",
        "username": "_mizdee"
      }
    },
    {
      "id": "17954216225961993",
      "text": "🔥🔥🔥",
      "ownerUsername": "kyo_extremelyblessed",
      "ownerProfilePicUrl": "https://instagram.fdet3-1.fna.fbcdn.net/v/t51.2885-19/468696019_1096406271591010_9061759517076402044_n.jpg?stp=dst-jpg_s150x150_tt6&efg=eyJ2ZW5jb2RlX3RhZyI6InByb2ZpbGVfcGljLmRqYW5nby4xMDgwLmMyIn0&_nc_ht=instagram.fdet3-1.fna.fbcdn.net&_nc_cat=110&_nc_oc=Q6cZ2gGcDjN5npyxElfFUSdPCD6m4Fw--OXXUQKkiHtEYawpHyrrRYgiNrWm42PMKCj_G_M&_nc_ohc=xKL76_UxLjMQ7kNvwGIfkzK&_nc_gid=1kEOHd-MKI879a4-KeQ-kQ&edm=APs17CUBAAAA&ccb=7-5&oh=00_Af1828_xtB7lfLioZu6-9ZTauDGEszc08TIKN2cwsFAUSw&oe=69F2A035&_nc_sid=10d13b",
      "timestamp": "2026-04-24T21:38:42.000Z",
      "repliesCount": 0,
      "replies": [],
      "likesCount": 0,
      "owner": {
        "id": "1723789106",
        "is_verified": false,
        "profile_pic_url": "https://instagram.fdet3-1.fna.fbcdn.net/v/t51.2885-19/468696019_1096406271591010_9061759517076402044_n.jpg?stp=dst-jpg_s150x150_tt6&efg=eyJ2ZW5jb2RlX3RhZyI6InByb2ZpbGVfcGljLmRqYW5nby4xMDgwLmMyIn0&_nc_ht=instagram.fdet3-1.fna.fbcdn.net&_nc_cat=110&_nc_oc=Q6cZ2gGcDjN5npyxElfFUSdPCD6m4Fw--OXXUQKkiHtEYawpHyrrRYgiNrWm42PMKCj_G_M&_nc_ohc=xKL76_UxLjMQ7kNvwGIfkzK&_nc_gid=1kEOHd-MKI879a4-KeQ-kQ&edm=APs17CUBAAAA&ccb=7-5&oh=00_Af1828_xtB7lfLioZu6-9ZTauDGEszc08TIKN2cwsFAUSw&oe=69F2A035&_nc_sid=10d13b",
        "username": "kyo_extremelyblessed"
      }
    },
    {
      "id": "18010794560895708",
      "text": "Judge got the vibe😂# 'Hip-hop hurray Judge'",
      "ownerUsername": "oluwatoyinoshinloye",
      "ownerProfilePicUrl": "https://instagram.fdet3-1.fna.fbcdn.net/v/t51.82787-19/558900796_18064869698598921_3013027122297372236_n.jpg?stp=dst-jpg_s150x150_tt6&efg=eyJ2ZW5jb2RlX3RhZyI6InByb2ZpbGVfcGljLmRqYW5nby42OTguYzIifQ&_nc_ht=instagram.fdet3-1.fna.fbcdn.net&_nc_cat=109&_nc_oc=Q6cZ2gGcDjN5npyxElfFUSdPCD6m4Fw--OXXUQKkiHtEYawpHyrrRYgiNrWm42PMKCj_G_M&_nc_ohc=IuLbeZ4Auu4Q7kNvwGREjue&_nc_gid=1kEOHd-MKI879a4-KeQ-kQ&edm=APs17CUBAAAA&ccb=7-5&oh=00_Af3PhXBjJs5c69nojqlDuTmiuqP9d6gM9luIG0jAm_xXRw&oe=69F2B0C5&_nc_sid=10d13b",
      "timestamp": "2026-04-24T16:41:42.000Z",
      "repliesCount": 1,
      "replies": [
        {
          "id": "18080831858626652",
          "text": "@oluwatoyinoshinloye 😂😂😂",
          "ownerUsername": "crix_cci",
          "ownerProfilePicUrl": "https://instagram.fdet3-1.fna.fbcdn.net/v/t51.2885-19/418621859_918076303042873_486651628991581195_n.jpg?stp=dst-jpg_s150x150_tt6&efg=eyJ2ZW5jb2RlX3RhZyI6InByb2ZpbGVfcGljLmRqYW5nby4xMDgwLmMyIn0&_nc_ht=instagram.fdet3-1.fna.fbcdn.net&_nc_cat=101&_nc_oc=Q6cZ2gGcDjN5npyxElfFUSdPCD6m4Fw--OXXUQKkiHtEYawpHyrrRYgiNrWm42PMKCj_G_M&_nc_ohc=jETMAlQZk3oQ7kNvwHIq8dY&_nc_gid=1kEOHd-MKI879a4-KeQ-kQ&edm=APs17CUBAAAA&ccb=7-5&oh=00_Af3C5CuBiKyYLgkzEaXK8E7N3paiEpVnNzbZhMTh6-JtNQ&oe=69F2BB10&_nc_sid=10d13b",
          "timestamp": "2026-04-24T16:51:29.000Z",
          "repliesCount": 0,
          "replies": [],
          "likesCount": 1,
          "owner": {
            "id": "2944346162",
            "is_verified": true,
            "profile_pic_url": "https://instagram.fdet3-1.fna.fbcdn.net/v/t51.2885-19/418621859_918076303042873_486651628991581195_n.jpg?stp=dst-jpg_s150x150_tt6&efg=eyJ2ZW5jb2RlX3RhZyI6InByb2ZpbGVfcGljLmRqYW5nby4xMDgwLmMyIn0&_nc_ht=instagram.fdet3-1.fna.fbcdn.net&_nc_cat=101&_nc_oc=Q6cZ2gGcDjN5npyxElfFUSdPCD6m4Fw--OXXUQKkiHtEYawpHyrrRYgiNrWm42PMKCj_G_M&_nc_ohc=jETMAlQZk3oQ7kNvwHIq8dY&_nc_gid=1kEOHd-MKI879a4-KeQ-kQ&edm=APs17CUBAAAA&ccb=7-5&oh=00_Af3C5CuBiKyYLgkzEaXK8E7N3paiEpVnNzbZhMTh6-JtNQ&oe=69F2BB10&_nc_sid=10d13b",
            "username": "crix_cci"
          }
        }
      ],
      "likesCount": 0,
      "owner": {
        "id": "47796694920",
        "is_verified": false,
        "profile_pic_url": "https://instagram.fdet3-1.fna.fbcdn.net/v/t51.82787-19/558900796_18064869698598921_3013027122297372236_n.jpg?stp=dst-jpg_s150x150_tt6&efg=eyJ2ZW5jb2RlX3RhZyI6InByb2ZpbGVfcGljLmRqYW5nby42OTguYzIifQ&_nc_ht=instagram.fdet3-1.fna.fbcdn.net&_nc_cat=109&_nc_oc=Q6cZ2gGcDjN5npyxElfFUSdPCD6m4Fw--OXXUQKkiHtEYawpHyrrRYgiNrWm42PMKCj_G_M&_nc_ohc=IuLbeZ4Auu4Q7kNvwGREjue&_nc_gid=1kEOHd-MKI879a4-KeQ-kQ&edm=APs17CUBAAAA&ccb=7-5&oh=00_Af3PhXBjJs5c69nojqlDuTmiuqP9d6gM9luIG0jAm_xXRw&oe=69F2B0C5&_nc_sid=10d13b",
        "username": "oluwatoyinoshinloye"
      }
    },
    {
      "id": "18095816258117845",
      "text": "😂😂😂😂😂",
      "ownerUsername": "_ichynadoll",
      "ownerProfilePicUrl": "https://instagram.fdet3-1.fna.fbcdn.net/v/t51.2885-19/484911383_4235480533347172_346062169099374160_n.jpg?stp=dst-jpg_s150x150_tt6&efg=eyJ2ZW5jb2RlX3RhZyI6InByb2ZpbGVfcGljLmRqYW5nby4xMDgwLmMyIn0&_nc_ht=instagram.fdet3-1.fna.fbcdn.net&_nc_cat=104&_nc_oc=Q6cZ2gGcDjN5npyxElfFUSdPCD6m4Fw--OXXUQKkiHtEYawpHyrrRYgiNrWm42PMKCj_G_M&_nc_ohc=pWrBpsTA4_gQ7kNvwG9NDmE&_nc_gid=1kEOHd-MKI879a4-KeQ-kQ&edm=APs17CUBAAAA&ccb=7-5&oh=00_Af3qUIFaKi56zrKMEZxg6_GGSG3f3SIL2u2tbafpN4noGA&oe=69F29C01&_nc_sid=10d13b",
      "timestamp": "2026-04-24T15:46:25.000Z",
      "repliesCount": 0,
      "replies": [],
      "likesCount": 0,
      "owner": {
        "id": "15020224",
        "is_verified": false,
        "profile_pic_url": "https://instagram.fdet3-1.fna.fbcdn.net/v/t51.2885-19/484911383_4235480533347172_346062169099374160_n.jpg?stp=dst-jpg_s150x150_tt6&efg=eyJ2ZW5jb2RlX3RhZyI6InByb2ZpbGVfcGljLmRqYW5nby4xMDgwLmMyIn0&_nc_ht=instagram.fdet3-1.fna.fbcdn.net&_nc_cat=104&_nc_oc=Q6cZ2gGcDjN5npyxElfFUSdPCD6m4Fw--OXXUQKkiHtEYawpHyrrRYgiNrWm42PMKCj_G_M&_nc_ohc=pWrBpsTA4_gQ7kNvwG9NDmE&_nc_gid=1kEOHd-MKI879a4-KeQ-kQ&edm=APs17CUBAAAA&ccb=7-5&oh=00_Af3qUIFaKi56zrKMEZxg6_GGSG3f3SIL2u2tbafpN4noGA&oe=69F29C01&_nc_sid=10d13b",
        "username": "_ichynadoll"
      }
    },
    {
      "id": "18437012431189717",
      "text": "Love this so much 😂😂😂😂",
      "ownerUsername": "sofiyawilhelm",
      "ownerProfilePicUrl": "https://instagram.fdet3-1.fna.fbcdn.net/v/t51.82787-19/626278542_18391687081146968_2549069981418006471_n.jpg?stp=dst-jpg_s150x150_tt6&efg=eyJ2ZW5jb2RlX3RhZyI6InByb2ZpbGVfcGljLmRqYW5nby4xMDA1LmMyIn0&_nc_ht=instagram.fdet3-1.fna.fbcdn.net&_nc_cat=108&_nc_oc=Q6cZ2gGcDjN5npyxElfFUSdPCD6m4Fw--OXXUQKkiHtEYawpHyrrRYgiNrWm42PMKCj_G_M&_nc_ohc=BWJZI_DMrMwQ7kNvwGh4l8a&_nc_gid=1kEOHd-MKI879a4-KeQ-kQ&edm=APs17CUBAAAA&ccb=7-5&oh=00_Af0T-dEJYPRSQryTxNTXjD55fhkjkhSNTjUby4pEbTInig&oe=69F2B452&_nc_sid=10d13b",
      "timestamp": "2026-04-24T09:17:50.000Z",
      "repliesCount": 0,
      "replies": [],
      "likesCount": 0,
      "owner": {
        "id": "4523642967",
        "is_verified": false,
        "profile_pic_url": "https://instagram.fdet3-1.fna.fbcdn.net/v/t51.82787-19/626278542_18391687081146968_2549069981418006471_n.jpg?stp=dst-jpg_s150x150_tt6&efg=eyJ2ZW5jb2RlX3RhZyI6InByb2ZpbGVfcGljLmRqYW5nby4xMDA1LmMyIn0&_nc_ht=instagram.fdet3-1.fna.fbcdn.net&_nc_cat=108&_nc_oc=Q6cZ2gGcDjN5npyxElfFUSdPCD6m4Fw--OXXUQKkiHtEYawpHyrrRYgiNrWm42PMKCj_G_M&_nc_ohc=BWJZI_DMrMwQ7kNvwGh4l8a&_nc_gid=1kEOHd-MKI879a4-KeQ-kQ&edm=APs17CUBAAAA&ccb=7-5&oh=00_Af0T-dEJYPRSQryTxNTXjD55fhkjkhSNTjUby4pEbTInig&oe=69F2B452&_nc_sid=10d13b",
        "username": "sofiyawilhelm"
      }
    },
    {
      "id": "17886538242374030",
      "text": "Congratulations to you both. The Judge 🫱🏼‍🫲🏾🫱🏼‍🫲🏾🫱🏼‍🫲🏾🫱🏼‍🫲🏾.",
      "ownerUsername": "mrshildasentell",
      "ownerProfilePicUrl": "https://instagram.fdet3-1.fna.fbcdn.net/v/t51.2885-19/487888913_678681744712286_5145385001013026034_n.jpg?stp=dst-jpg_s150x150_tt6&efg=eyJ2ZW5jb2RlX3RhZyI6InByb2ZpbGVfcGljLmRqYW5nby4xMDM3LmMyIn0&_nc_ht=instagram.fdet3-1.fna.fbcdn.net&_nc_cat=102&_nc_oc=Q6cZ2gGcDjN5npyxElfFUSdPCD6m4Fw--OXXUQKkiHtEYawpHyrrRYgiNrWm42PMKCj_G_M&_nc_ohc=H6Bjco-s0igQ7kNvwEKmx3y&_nc_gid=1kEOHd-MKI879a4-KeQ-kQ&edm=APs17CUBAAAA&ccb=7-5&oh=00_Af05cMQGGLnXvdgjVdhC4vVIU3b6Dm1slzYkNlxb2bArMQ&oe=69F2B09E&_nc_sid=10d13b",
      "timestamp": "2026-04-23T21:38:48.000Z",
      "repliesCount": 0,
      "replies": [],
      "likesCount": 0,
      "owner": {
        "id": "32291244248",
        "is_verified": false,
        "profile_pic_url": "https://instagram.fdet3-1.fna.fbcdn.net/v/t51.2885-19/487888913_678681744712286_5145385001013026034_n.jpg?stp=dst-jpg_s150x150_tt6&efg=eyJ2ZW5jb2RlX3RhZyI6InByb2ZpbGVfcGljLmRqYW5nby4xMDM3LmMyIn0&_nc_ht=instagram.fdet3-1.fna.fbcdn.net&_nc_cat=102&_nc_oc=Q6cZ2gGcDjN5npyxElfFUSdPCD6m4Fw--OXXUQKkiHtEYawpHyrrRYgiNrWm42PMKCj_G_M&_nc_ohc=H6Bjco-s0igQ7kNvwEKmx3y&_nc_gid=1kEOHd-MKI879a4-KeQ-kQ&edm=APs17CUBAAAA&ccb=7-5&oh=00_Af05cMQGGLnXvdgjVdhC4vVIU3b6Dm1slzYkNlxb2bArMQ&oe=69F2B09E&_nc_sid=10d13b",
        "username": "mrshildasentell"
      }
    },
    {
      "id": "17875404420454595",
      "text": "😍",
      "ownerUsername": "trb___ss",
      "ownerProfilePicUrl": "https://instagram.fdet3-1.fna.fbcdn.net/v/t51.82787-19/657230505_18081968399523214_9092103783180619738_n.jpg?stp=dst-jpg_s150x150_tt6&efg=eyJ2ZW5jb2RlX3RhZyI6InByb2ZpbGVfcGljLmRqYW5nby4xMDgwLmMyIn0&_nc_ht=instagram.fdet3-1.fna.fbcdn.net&_nc_cat=110&_nc_oc=Q6cZ2gGcDjN5npyxElfFUSdPCD6m4Fw--OXXUQKkiHtEYawpHyrrRYgiNrWm42PMKCj_G_M&_nc_ohc=ppd8_2ct3vQQ7kNvwEeMHp7&_nc_gid=1kEOHd-MKI879a4-KeQ-kQ&edm=APs17CUBAAAA&ccb=7-5&oh=00_Af2KvypksFlT41Ghf1YSUd_HvjEf42ZQivqPjKboAx0cDQ&oe=69F2CECD&_nc_sid=10d13b",
      "timestamp": "2026-04-23T17:43:08.000Z",
      "repliesCount": 0,
      "replies": [],
      "likesCount": 0,
      "owner": {
        "id": "45746923213",
        "is_verified": false,
        "profile_pic_url": "https://instagram.fdet3-1.fna.fbcdn.net/v/t51.82787-19/657230505_18081968399523214_9092103783180619738_n.jpg?stp=dst-jpg_s150x150_tt6&efg=eyJ2ZW5jb2RlX3RhZyI6InByb2ZpbGVfcGljLmRqYW5nby4xMDgwLmMyIn0&_nc_ht=instagram.fdet3-1.fna.fbcdn.net&_nc_cat=110&_nc_oc=Q6cZ2gGcDjN5npyxElfFUSdPCD6m4Fw--OXXUQKkiHtEYawpHyrrRYgiNrWm42PMKCj_G_M&_nc_ohc=ppd8_2ct3vQQ7kNvwEeMHp7&_nc_gid=1kEOHd-MKI879a4-KeQ-kQ&edm=APs17CUBAAAA&ccb=7-5&oh=00_Af2KvypksFlT41Ghf1YSUd_HvjEf42ZQivqPjKboAx0cDQ&oe=69F2CECD&_nc_sid=10d13b",
        "username": "trb___ss"
      }
    },
    {
      "id": "18097938914513832",
      "text": "😂",
      "ownerUsername": "afelix024",
      "ownerProfilePicUrl": "https://instagram.fdet3-1.fna.fbcdn.net/v/t51.82787-19/656697792_18352560733233660_7905712241301010387_n.jpg?stp=dst-jpg_s150x150_tt6&efg=eyJ2ZW5jb2RlX3RhZyI6InByb2ZpbGVfcGljLmRqYW5nby4xMDgwLmMyIn0&_nc_ht=instagram.fdet3-1.fna.fbcdn.net&_nc_cat=100&_nc_oc=Q6cZ2gGcDjN5npyxElfFUSdPCD6m4Fw--OXXUQKkiHtEYawpHyrrRYgiNrWm42PMKCj_G_M&_nc_ohc=2RtxWbTTnUoQ7kNvwEd36Yk&_nc_gid=1kEOHd-MKI879a4-KeQ-kQ&edm=APs17CUBAAAA&ccb=7-5&oh=00_Af1PhZcb4MV1F0klUmRe-Yz04GE1lltOemt1T9uN9SZuLQ&oe=69F2C793&_nc_sid=10d13b",
      "timestamp": "2026-04-23T15:24:22.000Z",
      "repliesCount": 0,
      "replies": [],
      "likesCount": 0,
      "owner": {
        "id": "7074225659",
        "is_verified": false,
        "profile_pic_url": "https://instagram.fdet3-1.fna.fbcdn.net/v/t51.82787-19/656697792_18352560733233660_7905712241301010387_n.jpg?stp=dst-jpg_s150x150_tt6&efg=eyJ2ZW5jb2RlX3RhZyI6InByb2ZpbGVfcGljLmRqYW5nby4xMDgwLmMyIn0&_nc_ht=instagram.fdet3-1.fna.fbcdn.net&_nc_cat=100&_nc_oc=Q6cZ2gGcDjN5npyxElfFUSdPCD6m4Fw--OXXUQKkiHtEYawpHyrrRYgiNrWm42PMKCj_G_M&_nc_ohc=2RtxWbTTnUoQ7kNvwEd36Yk&_nc_gid=1kEOHd-MKI879a4-KeQ-kQ&edm=APs17CUBAAAA&ccb=7-5&oh=00_Af1PhZcb4MV1F0klUmRe-Yz04GE1lltOemt1T9uN9SZuLQ&oe=69F2C793&_nc_sid=10d13b",
        "username": "afelix024"
      }
    }
  ],
  "dimensionsHeight": 1136,
  "dimensionsWidth": 640,
  "displayUrl": "https://instagram.fdet3-1.fna.fbcdn.net/v/t51.71878-15/671074975_1602611734360315_4056679459128970333_n.jpg?stp=dst-jpg_e15_tt6&_nc_ht=instagram.fdet3-1.fna.fbcdn.net&_nc_cat=107&_nc_oc=Q6cZ2gGcDjN5npyxElfFUSdPCD6m4Fw--OXXUQKkiHtEYawpHyrrRYgiNrWm42PMKCj_G_M&_nc_ohc=dk_3c8eIpgoQ7kNvwH0LvwE&_nc_gid=1kEOHd-MKI879a4-KeQ-kQ&edm=APs17CUBAAAA&ccb=7-5&oh=00_Af3U0CXYZ8vLyFreOi_iZyXuoiAErxjG6whYSE5np2c57w&oe=69F2BF82&_nc_sid=10d13b",
  "images": [],
  "videoUrl": "https://instagram.fdet3-1.fna.fbcdn.net/o1/v/t16/f2/m86/AQNuoUetRDthzTGj9BzayH6xQ_SG4o6TLkFzHtFBjK7ZVc-yuPhXX-_xNi0psB9ok2ShHiuVMc5U7RTg6uArODHwYQts1P1n2bMreZw.mp4?stp=dst-mp4&efg=eyJxZV9ncm91cHMiOiJbXCJpZ193ZWJfZGVsaXZlcnlfdnRzX290ZlwiXSIsInZlbmNvZGVfdGFnIjoidnRzX3ZvZF91cmxnZW4uY2xpcHMuYzIuNzIwLmJhc2VsaW5lIn0&_nc_cat=108&vs=1514162593654554_2270058346&_nc_vs=HBksFQIYUmlnX3hwdl9yZWVsc19wZXJtYW5lbnRfc3JfcHJvZC9EODQwRTlFODYwMEY3MjQ1QzM3RjgxQjZDNjU2M0I4MV92aWRlb19kYXNoaW5pdC5tcDQVAALIARIAFQIYUWlnX3hwdl9wbGFjZW1lbnRfcGVybWFuZW50X3YyLzA4NDRBNzRCQjU2MTRERjZEQURFNzQ3OEEyRDY1MDk0X2F1ZGlvX2Rhc2hpbml0Lm1wNBUCAsgBEgAoABgAGwAVAAAm8IuHjJ%2Fq5T8VAigCQzMsF0AiEOVgQYk3GBJkYXNoX2Jhc2VsaW5lXzFfdjERAHX%2BB2WWqQEA&_nc_rid=58119d9937&ccb=9-4&oh=00_Af1MgHl20AWTe33KUX2f2xe2-_ePEYZsWzv4DIIKVp5dMw&oe=69EED0F3&_nc_sid=10d13b",
  "audioUrl": "https://instagram.fdet3-1.fna.fbcdn.net/o1/v/t2/f2/m78/AQOnL39V7Ln8M5RBzXSRe4YVFh3YowetgAiTEcfpDHD8-0jVkoRHYpGi_bdgLYv82gas0n3ncXJcnoE8LgzYCqzQxccSSoozVn3mvK8.mp4?_nc_cat=108&_nc_oc=AdpFDgoVmomOtYiXs6YTXlDD2KIxvL6hjy5aUKWjQGWjY2WN96WUjWgYQqZ_BPyKA-o&_nc_sid=9ca052&_nc_ht=instagram.fdet3-1.fna.fbcdn.net&_nc_ohc=fbvqDzLmwfUQ7kNvwFHSeAE&efg=eyJ2ZW5jb2RlX3RhZyI6ImlnLXhwdmRzLmNsaXBzLmMyLUMzLmRhc2hfbG5faGVhYWNfdmJyM19hdWRpbyIsInZpZGVvX2lkIjpudWxsLCJvaWxfdXJsZ2VuX2FwcF9pZCI6OTM2NjE5NzQzMzkyNDU5LCJjbGllbnRfbmFtZSI6ImlnIiwieHB2X2Fzc2V0X2lkIjoxNzk1Njg1MDEyNzEwNjE2OCwiYXNzZXRfYWdlX2RheXMiOjUsInZpX3VzZWNhc2VfaWQiOjEwODI3LCJkdXJhdGlvbl9zIjo5LCJiaXRyYXRlIjo2NjE3MywidXJsZ2VuX3NvdXJjZSI6Ind3dyJ9&ccb=17-1&_nc_gid=1kEOHd-MKI879a4-KeQ-kQ&_nc_zt=28&_nc_ss=7a22e&oh=00_Af2ng9qYs3Oc0_tIHn0V3zZdavcU-72D71FJCzb-SljMFg&oe=69EEB861",
  "alt": null,
  "likesCount": 11334,
  "videoViewCount": 115907,
  "videoPlayCount": 257521,
  "timestamp": "2026-04-20T13:46:43.000Z",
  "childPosts": [],
  "locationName": "Frisco, Texas",
  "locationId": "234350279",
  "ownerFullName": "Crixpixels - Dallas Photographer and Videographer",
  "ownerUsername": "crix_cci",
  "ownerId": "2944346162",
  "productType": "clips",
  "videoDuration": 9.055,
  "taggedUsers": [
    {
      "full_name": "#ғᴏʀᴇᴍᴏsᴛᴡᴇᴅᴅɪɴɢᴘᴀɢᴇ",
      "id": "326381352",
      "is_verified": true,
      "profile_pic_url": "https://instagram.fdet3-1.fna.fbcdn.net/v/t51.82787-19/575511681_18540484234045353_6448513736760378623_n.jpg?stp=dst-jpg_s150x150_tt6&efg=eyJ2ZW5jb2RlX3RhZyI6InByb2ZpbGVfcGljLmRqYW5nby44MjguYzIifQ&_nc_ht=instagram.fdet3-1.fna.fbcdn.net&_nc_cat=109&_nc_oc=Q6cZ2gGcDjN5npyxElfFUSdPCD6m4Fw--OXXUQKkiHtEYawpHyrrRYgiNrWm42PMKCj_G_M&_nc_ohc=42CX6DtWwjAQ7kNvwFmtvOJ&_nc_gid=1kEOHd-MKI879a4-KeQ-kQ&edm=APs17CUBAAAA&ccb=7-5&oh=00_Af2vxgXv88siDKlKMzgmJAYfmS1LgsQ-qFFmRVwyZHGMQA&oe=69F2BC18&_nc_sid=10d13b",
      "username": "weddingdigestnaija"
    },
    {
      "full_name": "Crix Pixelsllc",
      "id": "8772766475",
      "is_verified": false,
      "profile_pic_url": "https://instagram.fdet3-1.fna.fbcdn.net/v/t51.2885-19/422509396_356345884011995_14153603078505013_n.jpg?stp=dst-jpg_s150x150_tt6&efg=eyJ2ZW5jb2RlX3RhZyI6InByb2ZpbGVfcGljLmRqYW5nby4xMDgwLmMyIn0&_nc_ht=instagram.fdet3-1.fna.fbcdn.net&_nc_cat=111&_nc_oc=Q6cZ2gGcDjN5npyxElfFUSdPCD6m4Fw--OXXUQKkiHtEYawpHyrrRYgiNrWm42PMKCj_G_M&_nc_ohc=B7pfLtWr8PEQ7kNvwF3mWW_&_nc_gid=1kEOHd-MKI879a4-KeQ-kQ&edm=APs17CUBAAAA&ccb=7-5&oh=00_Af29hkJxnSR9xlkSrTxtW5D4vB2iuuQ9xNszAenzZwtBSA&oe=69F2BF60&_nc_sid=10d13b",
      "username": "crix_pixels"
    }
  ],
  "musicInfo": {
    "artist_name": "crix_cci",
    "song_name": "Original audio",
    "uses_original_audio": true,
    "should_mute_audio": false,
    "should_mute_audio_reason": "",
    "audio_id": "34984993791146961"
  },
  "coauthorProducers": [
    {
      "id": "8772766475",
      "is_verified": false,
      "profile_pic_url": "https://instagram.fdet3-1.fna.fbcdn.net/v/t51.2885-19/422509396_356345884011995_14153603078505013_n.jpg?stp=dst-jpg_s150x150_tt6&efg=eyJ2ZW5jb2RlX3RhZyI6InByb2ZpbGVfcGljLmRqYW5nby4xMDgwLmMyIn0&_nc_ht=instagram.fdet3-1.fna.fbcdn.net&_nc_cat=111&_nc_oc=Q6cZ2gGcDjN5npyxElfFUSdPCD6m4Fw--OXXUQKkiHtEYawpHyrrRYgiNrWm42PMKCj_G_M&_nc_ohc=B7pfLtWr8PEQ7kNvwF3mWW_&_nc_gid=1kEOHd-MKI879a4-KeQ-kQ&edm=APs17CUBAAAA&ccb=7-5&oh=00_Af29hkJxnSR9xlkSrTxtW5D4vB2iuuQ9xNszAenzZwtBSA&oe=69F2BF60&_nc_sid=10d13b",
      "username": "crix_pixels"
    },
    {
      "id": "326381352",
      "is_verified": true,
      "profile_pic_url": "https://instagram.fdet3-1.fna.fbcdn.net/v/t51.82787-19/575511681_18540484234045353_6448513736760378623_n.jpg?stp=dst-jpg_s150x150_tt6&efg=eyJ2ZW5jb2RlX3RhZyI6InByb2ZpbGVfcGljLmRqYW5nby44MjguYzIifQ&_nc_ht=instagram.fdet3-1.fna.fbcdn.net&_nc_cat=109&_nc_oc=Q6cZ2gGcDjN5npyxElfFUSdPCD6m4Fw--OXXUQKkiHtEYawpHyrrRYgiNrWm42PMKCj_G_M&_nc_ohc=42CX6DtWwjAQ7kNvwFmtvOJ&_nc_gid=1kEOHd-MKI879a4-KeQ-kQ&edm=APs17CUBAAAA&ccb=7-5&oh=00_Af2vxgXv88siDKlKMzgmJAYfmS1LgsQ-qFFmRVwyZHGMQA&oe=69F2BC18&_nc_sid=10d13b",
      "username": "weddingdigestnaija"
    }
  ],
  "isCommentsDisabled": false
}